wallex/__init__.py
wallex/client.py
wallex/request.py
wallex/schema.py
wallex/utils.py
wallex_python-0.0.6.dist-info/LICENSE
wallex_python-0.0.6.dist-info/METADATA
wallex_python-0.0.6.dist-info/WHEEL
wallex_python-0.0.6.dist-info/top_level.txt
wallex_python-0.0.6.dist-info/RECORD
