Metadata-Version: 2.1
Name: wallex-python
Version: 0.0.6
Summary: Wallex Exchange Unofficial API Python Client
Home-page: https://github.com/wallexchange/wallex-python
Author: Pourya Moghadam
Author-email: p.moghadam@msn.com
License: MIT
Project-URL: Bug Tracker, https://github.com/wallexchange/wallex-python/issues
Project-URL: Documentation, https://api-docs.wallex.ir/
Project-URL: repository, https://github.com/wallexchange/wallex-python
Keywords: wallex crypto exchange api bitcoin ethereum btc eth python
Classifier: Intended Audience :: Developers
Classifier: License :: OSI Approved :: MIT License
Classifier: Operating System :: OS Independent
Classifier: Programming Language :: Python :: 3
Classifier: Programming Language :: Python :: 3.5
Classifier: Programming Language :: Python :: 3.6
Classifier: Programming Language :: Python :: 3.7
Classifier: Programming Language :: Python
Classifier: Topic :: Software Development :: Libraries :: Python Modules
Requires-Python: >=3.6
License-File: LICENSE
Requires-Dist: requests (==2.28.1)
Requires-Dist: pydantic (==1.9.2)
